tar_mak_monaco_report/Task6_report.py
tar_mak_monaco_report/__init__.py
tar_mak_monaco_report-0.2.0.dist-info/LICENSE
tar_mak_monaco_report-0.2.0.dist-info/METADATA
tar_mak_monaco_report-0.2.0.dist-info/WHEEL
tar_mak_monaco_report-0.2.0.dist-info/entry_points.txt
tar_mak_monaco_report-0.2.0.dist-info/top_level.txt
tar_mak_monaco_report-0.2.0.dist-info/RECORD
