Metadata-Version: 2.1
Name: tar_mak_monaco_report
Version: 0.2.0
Summary: a package that print monaco race report
Author-email: Taras Makutra <tarik9598@gmail.com>
Project-URL: Homepage, https://git.foxminded.ua/foxstudent106344/task-4-cli
Classifier: Programming Language :: Python :: 3
Classifier: License :: OSI Approved :: MIT License
Classifier: Operating System :: OS Independent
Requires-Python: >=3.8
License-File: LICENSE
